flask_migrate-stubs/METADATA.toml
flask_migrate-stubs/__init__.pyi
flask_migrate-stubs/py.typed
types_Flask_Migrate-4.1.0.20250112.dist-info/LICENSE
types_Flask_Migrate-4.1.0.20250112.dist-info/METADATA
types_Flask_Migrate-4.1.0.20250112.dist-info/WHEEL
types_Flask_Migrate-4.1.0.20250112.dist-info/top_level.txt
types_Flask_Migrate-4.1.0.20250112.dist-info/RECORD
